{
  "url": "https://vietnamnet.vn/rapper-binh-gold-duong-tinh-voi-ma-tuy-va-bi-csgt-truy-bat-tren-cao-toc-la-ai-2425199.html",
  "title": "Rapper Binh Gold duong tinh voi ma tuy va bi CSGT truy bat tren cao toc la ai?",
  "source": "VietnamNet",
  "published_at": "2025-07-24",
  "article_type": "news",
  "topic": "nghe si lien quan ma tuy",
  "content": "VietnamNet dua tin rapper Binh Gold, ten that Vu Xuan Binh, bi luc luong CSGT truy bat sau khi dieu khien oto co dau hieu lang lach, chen ep xe khac tren cao toc Noi Bai - Lao Cai. Bai viet cho biet qua test nhanh, rapper nay co ket qua duong tinh voi ma tuy. Bai viet cung tom luoc qua trinh hoat dong am nhac cua Binh Gold va cac san pham gay tranh cai.",
  "metadata": {
    "person": "Binh Gold",
    "legal_status": "bi CSGT kiem tra, duong tinh ma tuy",
    "substance_related": true
  },
  "crawl_date": "2026-06-08"
}